qingchat/__init__.py
qingchat/app.py
qingchat/cli.py
qingchat/friend.py
qingchat/group.py
qingchat/user.py
qingchat-0.3.2.dist-info/DESCRIPTION.rst
qingchat-0.3.2.dist-info/METADATA
qingchat-0.3.2.dist-info/RECORD
qingchat-0.3.2.dist-info/WHEEL
qingchat-0.3.2.dist-info/entry_points.txt
qingchat-0.3.2.dist-info/metadata.json
qingchat-0.3.2.dist-info/top_level.txt
