Metadata-Version: 2.0
Name: qingchat
Version: 0.3.2
Summary: Qingchat is a simple wechat framework, written in Python.
Home-page: https://xuanwo.org/
Author: Xuanwo
Author-email: xuanwo.cn@gmail.com
License: MIT License
Keywords: qingchat,wechat
Platform: UNKNOWN
Classifier: Development Status :: 4 - Beta
Classifier: Environment :: Console
Classifier: License :: OSI Approved :: MIT License
Classifier: Operating System :: MacOS
Classifier: Operating System :: POSIX
Classifier: Operating System :: POSIX :: Linux
Classifier: Operating System :: Microsoft :: Windows
Classifier: Programming Language :: Python
Classifier: Programming Language :: Python :: 3.4
Requires: requests
Requires: pyyaml
Requires: flask
Requires: docopt
Requires-Dist: docopt
Requires-Dist: pyyaml
Requires-Dist: requests
